llm_azure/__init__.py
llm_azure/anthropic.py
llm_azure/openai.py
llm_azure-2.0.dist-info/licenses/LICENSE
llm_azure-2.0.dist-info/METADATA
llm_azure-2.0.dist-info/WHEEL
llm_azure-2.0.dist-info/entry_points.txt
llm_azure-2.0.dist-info/top_level.txt
llm_azure-2.0.dist-info/RECORD
