Metadata-Version: 2.4
Name: llm-azure
Version: 2.0
Summary: Azure AI Foundry plugin for LLM - access Anthropic, Llama, Mistral and more via Azure
Author: Fabian Geiger
License-Expression: Apache-2.0
Project-URL: Homepage, https://github.com/fabge/llm-azure
Project-URL: Changelog, https://github.com/fabge/llm-azure/releases
Project-URL: Issues, https://github.com/fabge/llm-azure/issues
Project-URL: CI, https://github.com/fabge/llm-azure/actions
Requires-Python: >=3.10
License-File: LICENSE
Requires-Dist: llm>=0.22
Requires-Dist: azure-identity
Provides-Extra: anthropic
Requires-Dist: llm-anthropic; extra == "anthropic"
Dynamic: license-file
